fast_part/__init__.py
fast_part/fast_part.py
fast_part-0.1.dist-info/LICENSE
fast_part-0.1.dist-info/METADATA
fast_part-0.1.dist-info/WHEEL
fast_part-0.1.dist-info/entry_points.txt
fast_part-0.1.dist-info/top_level.txt
fast_part-0.1.dist-info/RECORD
